microplink/__init__.py
microplink/microplink.py
microplink-0.0.1.dist-info/LICENSE
microplink-0.0.1.dist-info/METADATA
microplink-0.0.1.dist-info/WHEEL
microplink-0.0.1.dist-info/top_level.txt
microplink-0.0.1.dist-info/RECORD
