Metadata-Version: 2.1
Name: microplink
Version: 0.0.1
Summary: PLINK file processing with numba
Home-page: https://github.com/ammodramus/microplink
Author: Peter Wilton
Author-email: peterrwilton@gmail.com
License: UNKNOWN
Platform: UNKNOWN
Classifier: Programming Language :: Python
Classifier: License :: OSI Approved :: MIT License
Classifier: Operating System :: OS Independent
Classifier: Topic :: Scientific/Engineering :: Bio-Informatics
Requires-Python: >=2.7
Requires-Dist: pandas
Requires-Dist: numpy
Requires-Dist: numba
